{
    "display": {
        "icon": {
            "id": "minecraft:clock",
            "components": {
                "minecraft:item_model": "aeternum:quest/enchanter"
            }
        },
        "title": {
            "translate": "aeternum.quests.start.name",
            "with": [
                "Enchanter"
            ],
            "italic": false
        },
        "description": {
            "translate": "aeternum.quests.start.enchanter_2",
            "italic": false
        },
        "show_toast": true,
        "announce_to_chat": false
    },
    "parent": "aeternum:quests/enchanter/enchanter_1",
    "criteria": {
        "start": {
            "trigger": "minecraft:impossible"
        },
        "end": {
            "trigger": "minecraft:impossible"
        }
    },
    "requirements": [
        [
            "start"
        ],
        [
            "end"
        ]
    ],
    "rewards": {
        "function": "aeternum:quests/reward"
    }
}